setup.py
hkhkhkhk/__init__.py
hkhkhkhk/cFunction.py
hkhkhkhk.egg-info/PKG-INFO
hkhkhkhk.egg-info/SOURCES.txt
hkhkhkhk.egg-info/dependency_links.txt
hkhkhkhk.egg-info/requires.txt
hkhkhkhk.egg-info/top_level.txt